{
    "id": "d107",
    "name": "Etir V",
    "aliases": [
        "etirv",
        "etir",
        "et",
        "4242"
    ],
    "imagePath": "d107.png",
    "shipPositionsType": "TYPE01",
    "spaceTokenLocations": [
        {
            "x": 195.0,
            "y": 10.0
        },
        {
            "x": 225.0,
            "y": 75.0
        },
        {
            "x": 225.0,
            "y": 155.0
        },
        {
            "x": 145.0,
            "y": 205.0
        }
    ],
    "wormholes": null,
    "planets": [
        "etirv"
    ],
    "source": "uncharted_space",
    "tileBack": "blue"
}