{
    "id": "er87",
    "name": "Argenum",
    "aliases": [
        "argenum",
        "arg",
        "vernium"
    ],
    "imagePath": "er_87_async.png",
    "shipPositionsType": "TYPE05",
    "spaceTokenLocations": [
        {
            "x": 180.0,
            "y": 0.0
        },
        {
            "x": 220.0,
            "y": 60.0
        },
        {
            "x": 45.0,
            "y": 120.0
        },
        {
            "x": 95.0,
            "y": 170.0
        }
    ],
    "wormholes": [],
    "planets": [
        "argenum",
        "vernium"
    ],
    "tileBack": "blue",
    "source": "eronous"
}