{
    "id": "er98",
    "name": "Mor Rock",
    "aliases": [
        "er98",
        "morrock",
        "migyro"
    ],
    "imagePath": "er_98_async.png",
    "planets": [
        "morrock",
        "migyro"
    ],
    "shipPositionsType": "TYPE05",
    "spaceTokenLocations": [
        {
            "x": 180.0,
            "y": 0.0
        },
        {
            "x": 220.0,
            "y": 60.0
        },
        {
            "x": 45.0,
            "y": 120.0
        },
        {
            "x": 95.0,
            "y": 170.0
        }
    ],
    "wormholes": null,
    "isAsteroidField": false,
    "isSupernova": false,
    "isNebula": false,
    "isGravityRift": false,
    "source": "eronous",
    "tileBack": "blue"
}