[
    {
        "id": "baldrick_carrier2",
        "baseType": "carrier",
        "asyncId": "cv",
        "name": "Carrier II",
        "upgradesFromUnitId": "carrier",
        "requiredTechId": "baldrick_cv2",
        "source": "ignis_aurora",
        "moveValue": 2,
        "capacityValue": 6,
        "cost": 3,
        "combatHitsOn": 9,
        "combatDieCount": 1,
        "isShip": true,
        "homebrewReplacesID": "carrier2"
    },
    {
        "id": "baldrick_sol_carrier2",
        "baseType": "carrier",
        "asyncId": "cv",
        "name": "Advanced Carrier 2",
        "upgradesFromUnitId": "sol_carrier",
        "requiredTechId": "baldrick_ac2",
        "source": "ignis_aurora",
        "faction": "Sol",
        "capacityValue": 8,
        "cost": 3,
        "combatHitsOn": 9,
        "combatDieCount": 1,
        "isShip": true,
        "homebrewReplacesID": "sol_carrier2"
    },
    {
        "id": "baldrick_dreadnought2",
        "baseType": "dreadnought",
        "asyncId": "dn",
        "name": "Dreadnought II",
        "upgradesFromUnitId": "dreadnought",
        "requiredTechId": "baldrick_dn2",
        "source": "ignis_aurora",
        "moveValue": 2,
        "capacityValue": 1,
        "cost": 4,
        "combatHitsOn": 5,
        "combatDieCount": 1,
        "bombardHitsOn": 5,
        "bombardDieCount": 1,
        "sustainDamage": true,
        "canBeDirectHit": true,
        "isShip": true,
        "homebrewReplacesID": "dreadnought2"
    },
    {
        "id": "baldrick_sardakk_dreadnought2",
        "baseType": "dreadnought",
        "asyncId": "dn",
        "name": "Exotrireme II",
        "upgradesFromUnitId": "sardakk_dreadnought",
        "requiredTechId": "baldrick_exo2",
        "source": "ignis_aurora",
        "faction": "Sardakk",
        "moveValue": 2,
        "capacityValue": 1,
        "cost": 4,
        "combatHitsOn": 5,
        "combatDieCount": 1,
        "bombardHitsOn": 4,
        "bombardDieCount": 2,
        "sustainDamage": true,
        "canBeDirectHit": true,
        "isShip": true,
        "homebrewReplacesID": "sardakk_dreadnought2",
        "ability": "After a round of space combat, you may destroy this unit to destroy up to 2 ships in this system."
    },
    {
        "id": "baldrick_l1z1x_dreadnought2",
        "baseType": "dreadnought",
        "asyncId": "dn",
        "name": "Super Dreadnought II",
        "upgradesFromUnitId": "l1z1x_dreadnought",
        "requiredTechId": "baldrick_sdn2",
        "source": "ignis_aurora",
        "faction": "L1Z1X",
        "moveValue": 2,
        "capacityValue": 2,
        "cost": 4,
        "combatHitsOn": 4,
        "combatDieCount": 1,
        "bombardHitsOn": 4,
        "bombardDieCount": 1,
        "sustainDamage": true,
        "canBeDirectHit": true,
        "isShip": true,
        "homebrewReplacesID": "l1z1x_dreadnought2"
    },
    {
        "id": "baldrick_fighter2",
        "baseType": "fighter",
        "asyncId": "ff",
        "name": "Fighter II",
        "upgradesFromUnitId": "fighter",
        "requiredTechId": "baldrick_ff2",
        "source": "ignis_aurora",
        "moveValue": 2,
        "capacityUsed": 1,
        "cost": 0.5,
        "combatHitsOn": 8,
        "combatDieCount": 1,
        "isShip": true,
        "homebrewReplacesID": "fighter2",
        "ability": "This unit may move without being transported. Fighters in excess of your ships' capacity count against your fleet pool."
    },
    {
        "id": "baldrick_naalu_fighter2",
        "baseType": "fighter",
        "asyncId": "ff",
        "name": "Hybrid Crystal Fighter II",
        "upgradesFromUnitId": "naalu_fighter",
        "requiredTechId": "baldrick_hcf2",
        "source": "ignis_aurora",
        "faction": "Naalu",
        "moveValue": 2,
        "capacityUsed": 1,
        "cost": 0.5,
        "combatHitsOn": 7,
        "combatDieCount": 1,
        "isShip": true,
        "homebrewReplacesID": "naalu_fighter2",
        "ability": "This unit may move without being transported. Each fighter in excess of your ships' capacity counts as 1/2 of a ship against your fleet pool."
    },
    {
        "id": "baldrick_infantry2",
        "baseType": "infantry",
        "asyncId": "gf",
        "name": "Infantry II",
        "requiredTechId": "baldrick_inf2",
        "source": "ignis_aurora",
        "isGroundForce": true,
        "homebrewReplacesID": "infantry2",
        "ability": "You may produce 1 additional infantry for their cost. These infantry do not count against your production limit."
    },
    {
        "id": "baldrick_sol_infantry2",
        "baseType": "infantry",
        "asyncId": "gf",
        "name": "Spec Ops II",
        "upgradesFromUnitId": "sol_infantry",
        "requiredTechId": "baldrick_so2",
        "source": "ignis_aurora",
        "faction": "Sol",
        "capacityUsed": 1,
        "cost": 0.5,
        "combatHitsOn": 6,
        "combatDieCount": 1,
        "isGroundForce": true,
        "homebrewReplacesID": "sol_infantry2",
        "ability": "You may produce 1 additional infantry for their cost. These infantry do not count against your production limit."
    },
    {
        "id": "baldrick_mahact_infantry2",
        "baseType": "infantry",
        "asyncId": "gf",
        "name": "Crimson Legionnaire II",
        "upgradesFromUnitId": "mahact_infantry",
        "requiredTechId": "baldrick_cl2",
        "source": "ignis_aurora",
        "faction": "Mahact",
        "capacityUsed": 1,
        "cost": 0.5,
        "combatHitsOn": 7,
        "combatDieCount": 1,
        "isGroundForce": true,
        "homebrewReplacesID": "mahact_infantry2",
        "ability": "After this unit is destroyed, gain 1 commodity or convert 1 of your commodities to a trade good. You may produce 1 additional infantry for their cost. These infantry do not count against your production limit."
    },
    {
        "id": "baldrick_pds2",
        "baseType": "pds",
        "asyncId": "pd",
        "name": "PDS II",
        "upgradesFromUnitId": "pds",
        "requiredTechId": "baldrick_pds2",
        "source": "ignis_aurora",
        "spaceCannonHitsOn": 6,
        "spaceCannonDieCount": 1,
        "deepSpaceCannon": true,
        "planetaryShield": true,
        "isStructure": true,
        "homebrewReplacesID": "pds2",
        "ability": "You may use this unit's Space Cannon against ships that are adjacent to this unit's system. When your units use Space Cannon, at least half of the hits produced by those units (rounded up) must be assigned to non-fighter ships if able. "
    },
    {
        "id": "baldrick_titans_pds2",
        "baseType": "pds",
        "asyncId": "pd",
        "name": "Hel-Titan II",
        "upgradesFromUnitId": "titans_pds",
        "requiredTechId": "baldrick_ht2",
        "source": "ignis_aurora",
        "faction": "Titans",
        "productionValue": 1,
        "combatHitsOn": 6,
        "combatDieCount": 1,
        "spaceCannonHitsOn": 6,
        "spaceCannonDieCount": 1,
        "deepSpaceCannon": true,
        "planetaryShield": true,
        "sustainDamage": true,
        "isStructure": true,
        "isGroundForce": true,
        "homebrewReplacesID": "titans_pds2",
        "ability": "This unit is treated as both a structure and a ground force. It cannot be transported. \nYou may use this unit's Space Cannon against ships that are adjacent to this unit's system.\nWhen your units use Space Cannon, at least half of the hits produced by those units (rounded up) must be assigned to non-fighter ships if able."
    },
    {
        "id": "baldrick_spacedock2",
        "baseType": "spacedock",
        "asyncId": "sd",
        "name": "Space Dock II",
        "upgradesFromUnitId": "spacedock",
        "requiredTechId": "baldrick_sd2",
        "source": "ignis_aurora",
        "productionValue": "+5",
        "capacityValue": 6,
        "isStructure": true,
        "homebrewReplacesID": "spacedock2"
    },
    {
        "id": "baldrick_warsun",
        "baseType": "warsun",
        "asyncId": "ws",
        "name": "War Sun",
        "requiredTechId": "baldrick_ws",
        "source": "ignis_aurora",
        "moveValue": 2,
        "capacityValue": 8,
        "cost": 10,
        "combatHitsOn": 3,
        "combatDieCount": 3,
        "bombardHitsOn": 3,
        "bombardDieCount": 3,
        "sustainDamage": true,
        "disablesPlanetaryShield": true,
        "canBeDirectHit": true,
        "isShip": true,
        "homebrewReplacesID": "warsun",
        "ability": "Other players units in this system lose PLANETARY SHIELD ability."
    },
    {
        "id": "baldrick_muaat_warsun",
        "baseType": "warsun",
        "asyncId": "ws",
        "name": "War Sun",
        "upgradesFromUnitId": "muaat_warsun",
        "requiredTechId": "baldrick_pws2",
        "source": "ignis_aurora",
        "moveValue": 3,
        "capacityValue": 8,
        "cost": 10,
        "combatHitsOn": 3,
        "combatDieCount": 3,
        "bombardHitsOn": 3,
        "bombardDieCount": 3,
        "sustainDamage": true,
        "disablesPlanetaryShield": true,
        "canBeDirectHit": false,
        "isShip": true,
        "homebrewReplacesID": "muaat_warsun",
        "ability": "Other players units in this system lose PLANETARY SHIELD ability. This unit cannot be destroyed by Direct Hit action cards."
    }
]
