[
    {
        "id": "netharii_inf",
        "baseType": "infantry",
        "asyncId": "gf",
        "name": "Sentinel I",
        "upgradesToUnitId": "netharii_inf2",
        "source": "memephilosopher",
        "faction": "netharii",
        "cost": 1,
        "combatHitsOn": 6,
        "combatDieCount": 1,
        "isGroundForce": true,
        "ability": "This unit can only use SPACE CANNON if on a planet.",
        "spaceCannonHitsOn": 7,
        "spaceCannonDieCount": 1
    },
    {
        "id": "netharii_inf2",
        "baseType": "infantry",
        "asyncId": "gf",
        "name": "Sentinel II",
        "upgradesFromUnitId": "netharii_inf",
        "source": "memephilosopher",
        "faction": "netharii",
        "cost": 1,
        "combatHitsOn": 5,
        "combatDieCount": 1,
        "isGroundForce": true,
        "ability": "This unit can only use SPACE CANNON if on a planet. You may use this unit's SPACE CANNON against ships that are adjacent to this unit's system.",
        "spaceCannonHitsOn": 6,
        "spaceCannonDieCount": 1,
        "deepSpaceCannon": true
    },
    {
        "id": "netharii_fs",
        "baseType": "flagship",
        "asyncId": "fs",
        "name": "The Eternal Vanguard",
        "source": "memephilosopher",
        "faction": "netharii",
        "moveValue": 1,
        "capacityValue": 3,
        "cost": 8,
        "combatHitsOn": 7,
        "combatDieCount": 2,
        "bombardHitsOn": 5,
        "bombardDieCount": 3,
        "sustainDamage": true,
        "canBeDirectHit": true,
        "isShip": true,
        "ability": "When in combat, gain 1 trade good for each of your non-fighter ships destroyed in this system."
    },
    {
        "id": "netharii_mech",
        "baseType": "mech",
        "asyncId": "mf",
        "name": "Aeternus",
        "source": "memephilosopher",
        "faction": "netharii",
        "cost": 2,
        "combatHitsOn": 6,
        "combatDieCount": 1,
        "sustainDamage": true,
        "ability": "When this unit is destroyed, gain one trade good."
    }
]