[
    {
        "alias": "lgy",
        "name": "lightgray",
        "aliases": ["lgy", "lightgrey", "white", "W"],
        "textColor": "black",
        "primaryColor": { "red": 206, "green": 206, "blue": 206 },
        "hue": "GRAY"
    },
    {
        "alias": "red",
        "name": "red",
        "aliases": ["red"],
        "textColor": "white",
        "primaryColor": { "red": 240, "green": 6, "blue": 6 },
        "hue": "RED"
    },
    {
        "alias": "org",
        "name": "orange",
        "aliases": ["orange", "E", "org"],
        "textColor": "black",
        "primaryColor": { "red": 240, "green": 180, "blue": 6 },
        "hue": "ORANGE"
    },
    {
        "alias": "ylw",
        "name": "yellow",
        "aliases": ["yellow", "Y", "ylw"],
        "textColor": "black",
        "primaryColor": { "red": 245, "green": 245, "blue": 6 },
        "hue": "YELLOW"
    },
    {
        "alias": "grn",
        "name": "green",
        "aliases": ["green", "grn"],
        "textColor": "white",
        "primaryColor": { "red": 6, "green": 175, "blue": 50 },
        "hue": "GREEN"
    },
    {
        "alias": "blu",
        "name": "blue",
        "aliases": ["blue", "blu"],
        "textColor": "white",
        "primaryColor": { "red": 6, "green": 75, "blue": 203 },
        "hue": "BLUE"
    },
    {
        "alias": "ppl",
        "name": "purple",
        "aliases": ["purple", "P", "ppl"],
        "textColor": "white",
        "primaryColor": { "red": 146, "green": 6, "blue": 186 },
        "hue": "PURPLE"
    },
    {
        "alias": "pnk",
        "name": "pink",
        "aliases": ["pink", "K", "pnk"],
        "textColor": "black",
        "primaryColor": { "red": 240, "green": 138, "blue": 240 },
        "hue": "PINK"
    },
    {
        "alias": "blk",
        "name": "black",
        "aliases": ["black", "blk"],
        "textColor": "white",
        "primaryColor": { "red": 50, "green": 50, "blue": 50 },
        "hue": "GRAY"
    },
    {
        "alias": "ptr",
        "name": "petrol",
        "aliases": ["ptr"],
        "textColor": "white",
        "primaryColor": { "red": 66, "green": 140, "blue": 140 },
        "hue": "BLUE"
    },
    {
        "alias": "rst",
        "name": "rust",
        "aliases": ["rst"],
        "textColor": "white",
        "primaryColor": { "red": 140, "green": 66, "blue": 72 },
        "hue": "RED"
    },
    {
        "alias": "bwn",
        "name": "brown",
        "aliases": ["bwn"],
        "textColor": "white",
        "primaryColor": { "red": 150, "green": 80, "blue": 42 },
        "hue": "ORANGE"
    },
    {
        "alias": "gry",
        "name": "gray",
        "aliases": ["gray", "grey", "gry"],
        "textColor": "white",
        "primaryColor": { "red": 110, "green": 122, "blue": 150 },
        "hue": "GRAY"
    },
    {
        "alias": "tan",
        "name": "tan",
        "aliases": ["tan"],
        "textColor": "black",
        "primaryColor": { "red": 172, "green": 160, "blue": 116 },
        "hue": "ORANGE"
    },
    {
        "alias": "frs",
        "name": "forest",
        "aliases": ["frs"],
        "textColor": "white",
        "primaryColor": { "red": 90, "green": 150, "blue": 100 },
        "hue": "GREEN"
    },
    {
        "alias": "plm",
        "name": "plum",
        "aliases": ["plm"],
        "textColor": "white",
        "primaryColor": { "red": 150, "green": 90, "blue": 140 },
        "hue": "PURPLE"
    },
    {
        "alias": "tea",
        "name": "teal",
        "aliases": ["tea"],
        "textColor": "black",
        "primaryColor": { "red": 0, "green": 235, "blue": 255 },
        "hue": "BLUE"
    },
    {
        "alias": "rse",
        "name": "rose",
        "aliases": ["rse"],
        "textColor": "black",
        "primaryColor": { "red": 217, "green": 165, "blue": 229 },
        "hue": "PINK"
    },
    {
        "alias": "lme",
        "name": "lime",
        "aliases": ["lme"],
        "textColor": "black",
        "primaryColor": { "red": 177, "green": 229, "blue": 165 },
        "hue": "GREEN"
    },
    {
        "alias": "lvn",
        "name": "lavender",
        "aliases": ["lvn"],
        "textColor": "black",
        "primaryColor": { "red": 169, "green": 167, "blue": 231 },
        "hue": "PURPLE"
    },
    {
        "alias": "spr",
        "name": "spring",
        "aliases": ["spr"],
        "textColor": "black",
        "primaryColor": { "red": 219, "green": 231, "blue": 167 },
        "hue": "YELLOW"
    },
    {
        "alias": "pch",
        "name": "peach",
        "aliases": ["pch"],
        "textColor": "black",
        "primaryColor": { "red": 232, "green": 184, "blue": 167 },
        "hue": "ORANGE"
    },
    {
        "alias": "eth",
        "name": "ethereal",
        "aliases": ["eth"],
        "textColor": "black",
        "primaryColor": { "red": 35, "green": 104, "blue": 200 },
        "hue": "BLUE"
    }
]
