{
    "id": "phlegethon",
    "tileId": "fracture7",
    "name": "Phlegethon",
    "aliases": [
        "phlegethon",
        "plem",
        "phlem",
        "phleg",
        "pleg",
        "plegethon"
    ],
    "resources": 1,
    "influence": 2,
    "planetTypes": [
        "LIGHTNING"
    ],
    "planetLayout": {
        "unitHolderName": "phlegethon",
        "resourcesLocation": "BottomRight",
        "centerPosition": {
            "x": 205.0,
            "y": 206.0
        }
    },
    "source": "thunders_edge"
}