{
    "id": "thibah",
    "tileId": "21",
    "name": "Thibah",
    "shortName": null,
    "aliases": [
        "thibah",
        "thiba",
        "thibh",
        "tibah",
        "tiba",
        "21_1"
    ],
    "positionInTile": {
        "x": 172.0,
        "y": 148.0
    },
    "resources": 1,
    "influence": 1,
    "factionHomeworld": null,
    "planetType": "INDUSTRIAL",
    "cardImagePath": null,
    "techSpecialties": [
        "PROPULSION"
    ],
    "legendaryAbilityName": null,
    "legendaryAbilityText": null,
    "unitPositions": {
        "unitHolderName": "thibah",
        "coordinateMap": {
            "control": [
                {
                    "x": 135.0,
                    "y": 138.0
                }
            ],
            "sd": [
                {
                    "x": 195.0,
                    "y": 173.0
                }
            ],
            "pd": [
                {
                    "x": 140.0,
                    "y": 165.0
                },
                {
                    "x": 157.0,
                    "y": 165.0
                },
                {
                    "x": 174.0,
                    "y": 165.0
                },
                {
                    "x": 149.0,
                    "y": 176.0
                },
                {
                    "x": 167.0,
                    "y": 176.0
                }
            ],
            "mf": [
                {
                    "x": 142.0,
                    "y": 94.0
                },
                {
                    "x": 160.0,
                    "y": 94.0
                },
                {
                    "x": 135.0,
                    "y": 107.0
                },
                {
                    "x": 153.0,
                    "y": 107.0
                },
                {
                    "x": 171.0,
                    "y": 107.0
                }
            ],
            "tkn_gf": [
                {
                    "x": 154.0,
                    "y": 135.0
                },
                {
                    "x": 121.0,
                    "y": 135.0
                }
            ],
            "att": [
                {
                    "x": 78.0,
                    "y": 127.0
                },
                {
                    "x": 86.0,
                    "y": 96.0
                },
                {
                    "x": 205.0,
                    "y": 127.0
                },
                {
                    "x": 197.0,
                    "y": 96.0
                }
            ]
        },
        "removeUnitCoordinate": true
    },
    "flavourText": "*Burdened by overpopulation and low mineral content in the planetary crust. Historically used as a staging world for deep-space exploration and trade.*",
    "source": "base"
}