[
    {
        "alias": "lazax",
        "factionName": "Lazax",
        "shortTag": "LAZ",
        "homeSystem": "",
        "startingFleet": "",
        "commodities": 0,
        "factionTech": [],
        "startingTech": [],
        "homePlanets": [],
        "abilities": [],
        "leaders": [],
        "promissoryNotes": [],
        "units": [
            "fighter",
            "destroyer",
            "cruiser",
            "carrier",
            "dreadnought",
            "flagship",
            "infantry",
            "mech",
            "pds",
            "spacedock"
        ],
        "source": "lazax"
    },
    {
        "alias": "neutral",
        "factionName": "Neutral",
        "shortTag": "NEU",
        "homeSystem": "",
        "startingFleet": "",
        "commodities": 0,
        "factionTech": [],
        "startingTech": [],
        "homePlanets": [],
        "abilities": [],
        "leaders": [],
        "promissoryNotes": [],
        "units": [
            "fighter",
            "destroyer",
            "cruiser",
            "carrier",
            "dreadnought",
            "flagship",
            "infantry",
            "mech",
            "pds",
            "spacedock"
        ],
        "source": "neutral"
    },
    {
        "alias": "admins",
        "factionName": "The Admins of Asyncia",
        "homeSystem": "s14",
        "startingFleet": "3 inf t,2 ff,cv,2 dd,sd t",
        "commodities": 3,
        "factionTech": [],
        "startingTech": ["sar", "gd"],
        "homePlanets": ["somna", "tera", "hospoona"],
        "abilities": [],
        "leaders": ["adminsagent", "adminscommander", "adminshero"],
        "promissoryNotes": ["adminspn"],
        "units": [
            "fighter",
            "destroyer",
            "cruiser",
            "carrier",
            "dreadnought",
            "admins_flagship",
            "infantry",
            "admins_mech",
            "pds",
            "admins_spacedock"
        ],
        "source": "admins"
    }
]
